rivers2stratigraphy/__init__.py
rivers2stratigraphy/_version.py
rivers2stratigraphy/channel.py
rivers2stratigraphy/geom.py
rivers2stratigraphy/gui.py
rivers2stratigraphy/sedtrans.py
rivers2stratigraphy/slider_manager.py
rivers2stratigraphy/strat.py
rivers2stratigraphy/utils.py
rivers2stratigraphy/widgets.py
rivers2stratigraphy-0.3.18.dist-info/LICENSE.txt
rivers2stratigraphy-0.3.18.dist-info/METADATA
rivers2stratigraphy-0.3.18.dist-info/WHEEL
rivers2stratigraphy-0.3.18.dist-info/top_level.txt
rivers2stratigraphy-0.3.18.dist-info/RECORD
