Metadata-Version: 2.1
Name: rivers2stratigraphy
Version: 0.3.18
Summary: educational activity for teaching how rivers become stratigraphy
Home-page: https://github.com/sededu/rivers2stratigraphy
Author: Andrew J. Moodie
Author-email: amoodie@rice.edu
License: LICENSE.txt
Project-URL: Bug Reports, https://github.com/sededu/rivers2stratigraphy/issues
Project-URL: Source, https://github.com/sededu/rivers2stratigraphy
Platform: UNKNOWN
Classifier: Development Status :: 4 - Beta
Classifier: License :: OSI Approved :: MIT License
Classifier: Intended Audience :: Education
Classifier: Intended Audience :: End Users/Desktop
Classifier: Intended Audience :: Science/Research
Classifier: Topic :: Education
Requires-Python: >=3
License-File: LICENSE.txt
Requires-Dist: scipy
Requires-Dist: numpy
Requires-Dist: matplotlib
Requires-Dist: shapely
